AUTHORS.rst
CONTRIBUTING.rst
HISTORY.rst
LICENSE
MANIFEST.in
README.rst
setup.cfg
setup.py
bitfield_manager/__init__.py
bitfield_manager/apps.py
bitfield_manager/models.py
bitfield_manager/utils.py
bitfield_manager/views.py
django_bitfield_manager.egg-info/PKG-INFO
django_bitfield_manager.egg-info/SOURCES.txt
django_bitfield_manager.egg-info/dependency_links.txt
django_bitfield_manager.egg-info/not-zip-safe
django_bitfield_manager.egg-info/top_level.txt