Metadata-Version: 1.1
Name: django-bitfield-manager
Version: 0.3.0
Summary: Your project description goes here
Home-page: https://github.com/goodmase/django-bitfield-manager
Author: Stephen Goodman
Author-email: stephen.goodman@gmail.com
License: MIT
Keywords: django-bitfield-manager
Platform: UNKNOWN
Classifier: Development Status :: 3 - Alpha
Classifier: Framework :: Django
Classifier: Framework :: Django :: 1.8
Classifier: Framework :: Django :: 1.9
Classifier: Framework :: Django :: 1.10
Classifier: Intended Audience :: Developers
Classifier: License :: OSI Approved :: BSD License
Classifier: Natural Language :: English
Classifier: Programming Language :: Python :: 2
Classifier: Programming Language :: Python :: 2.7
Classifier: Programming Language :: Python :: 3
Classifier: Programming Language :: Python :: 3.3
Classifier: Programming Language :: Python :: 3.4
Classifier: Programming Language :: Python :: 3.5
